regreg-0.1.3.dist-info/WHEEL
regreg-0.1.3.dist-info/top_level.txt
regreg-0.1.3.dist-info/METADATA
regreg-0.1.3.dist-info/RECORD
regreg/objdoctemplates.py
regreg/algorithms.py
regreg/info.py
regreg/api.py
regreg/__init__.py
regreg/identity_quadratic.py
regreg/paths.py
regreg/_version.py
regreg/doctemplates.py
regreg/smooth/losses.py
regreg/smooth/__init__.py
regreg/smooth/quadratic.py
regreg/smooth/glm.py
regreg/smooth/tests/test_multinomial.py
regreg/smooth/tests/__init__.py
regreg/smooth/tests/test_compareR.py
regreg/smooth/tests/test_glm.py
regreg/smooth/tests/test_logistic.py
regreg/smooth/tests/test_losses.py
regreg/atoms/cones.py
regreg/atoms/seminorms.py
regreg/atoms/svd_norms.py
regreg/atoms/piecewise_linear.so
regreg/atoms/group_lasso.py
regreg/atoms/projl1_cython.so
regreg/atoms/_isotonic_py.py
regreg/atoms/__init__.py
regreg/atoms/mixed_lasso.py
regreg/atoms/linear_constraints.py
regreg/atoms/slope.py
regreg/atoms/mixed_lasso_cython.so
regreg/atoms/sparse_group_lasso.py
regreg/atoms/block_norms.py
regreg/atoms/weighted_atoms.py
regreg/atoms/tests/test_group_lasso.py
regreg/atoms/tests/test_slope_compareR.py
regreg/atoms/tests/test_atom_classmethods.py
regreg/atoms/tests/test_seminorms.py
regreg/atoms/tests/test_weighted_atoms.py
regreg/atoms/tests/test_cones.py
regreg/atoms/tests/__init__.py
regreg/atoms/tests/test_sparse_group_lasso.py
regreg/atoms/tests/test_matrix_norms.py
regreg/atoms/tests/test_linear_constraints.py
regreg/atoms/tests/test_slope.py
regreg/atoms/tests/test_mixed_lasso.py
regreg/atoms/tests/test_affine.py
regreg/affine/factored_matrix.py
regreg/affine/fused_lasso.py
regreg/affine/__init__.py
regreg/affine/multiscale.py
regreg/affine/image2d.py
regreg/affine/tests/test_factored_matrix.py
regreg/affine/tests/test_normalize.py
regreg/affine/tests/__init__.py
regreg/affine/tests/test_fused_lasso.py
regreg/affine/tests/test_image2d.py
regreg/affine/tests/test_multiscale.py
regreg/affine/tests/test_affine.py
regreg/tests/test_doctemplates.py
regreg/tests/decorators.py
regreg/tests/__init__.py
